stencil/__init__.py
stencil/cli.py
stencil/curses_backend.py
stencil/flutter_backend.py
stencil/html_backend.py
stencil/imgui_backend.py
stencil/main.py
stencil/react_backend.py
stencil/abstract_classes/Button.py
stencil/abstract_classes/Component.py
stencil/abstract_classes/Input.py
stencil/abstract_classes/Separator.py
stencil/abstract_classes/Textbox.py
stencil/abstract_classes/Title.py
stencil_ui-1.0.0.dist-info/licenses/LICENSE
stencil_ui-1.0.0.dist-info/METADATA
stencil_ui-1.0.0.dist-info/WHEEL
stencil_ui-1.0.0.dist-info/entry_points.txt
stencil_ui-1.0.0.dist-info/top_level.txt
stencil_ui-1.0.0.dist-info/RECORD
