Metadata-Version: 2.4
Name: stencil-ui
Version: 1.0.0
Summary: CLI tool to generate UI code for multiple backends like HTML, React, Flutter, ImGui, and Curses from a simple config file
Author: Krishanth K
License: MIT License
Requires-Python: >=3.9
License-File: LICENSE
Requires-Dist: PyYAML>=6.0.3
Requires-Dist: watchdog>=3.0.0
Provides-Extra: imgui
Requires-Dist: glfw; extra == "imgui"
Requires-Dist: PyOpenGL; extra == "imgui"
Requires-Dist: imgui[glfw]; extra == "imgui"
Dynamic: license-file
